{
  "responses": {
    "200": {
      "description": "Getting Policy List",
      "content": {
        "application/json": {
          "schema": {
            "type": "object",
            "properties": {
              "result": {
                "type": "array",
                "items": {
                  "type": "object",
                  "properties": {
                    "active": {
                      "type": "boolean",
                      "description": "Indicates if the policy is active",
                      "example": true
                    },
                    "id": { "type": "string", "example": "654a7e62a34b9c000006886c2" },
                    "profile": { "type": "string", "example": "62fa9e65e0badb0019200" },
                    "name": { "type": "string", "example": "My Analysis Policy" },
                    "created_at": {
                      "type": "string",
                      "description": "Date and time when the policy was created",
                      "example": "2023-11-01T12:34:56.789Z"
                    },
                    "tags": { "type": "array", "items": {}, "example": [] }
                  }
                }
              },
              "status": { "type": "boolean", "example": true }
            }
          }
        }
      }
    }
  }
}
